access_med_utils/CMORise.py
access_med_utils/__init__.py
access_med_utils/_version.py
access_med_utils/app_functions.py
access_med_utils/hackathon.py
access_med_utils/ilamb.py
access_med_utils/utilities.py
access_med_utils-0.1.12.dist-info/licenses/LICENSE
access_med_utils-0.1.12.dist-info/METADATA
access_med_utils-0.1.12.dist-info/WHEEL
access_med_utils-0.1.12.dist-info/entry_points.txt
access_med_utils-0.1.12.dist-info/top_level.txt
access_med_utils-0.1.12.dist-info/RECORD
